pyparsing/__init__.py
pyparsing/actions.py
pyparsing/common.py
pyparsing/core.py
pyparsing/exceptions.py
pyparsing/helpers.py
pyparsing/results.py
pyparsing/testing.py
pyparsing/unicode.py
pyparsing/util.py
pyparsing/diagram/__init__.py
pyparsing/diagram/template.jinja2
pyparsing-3.0.5.dist-info/LICENSE
pyparsing-3.0.5.dist-info/METADATA
pyparsing-3.0.5.dist-info/WHEEL
pyparsing-3.0.5.dist-info/top_level.txt
pyparsing-3.0.5.dist-info/RECORD
